<?xml version="1.0" encoding="UTF-8"?>
<profilesXml xmlns="http://maven.apache.org/PROFILES/1.0.0"
             xmlns:xsi="http://www.w3.org/2001/XMLSchema-instance"
             xsi:schemaLocation="http://maven.apache.org/PROFILES/1.0.0 http://maven.apache.org/xsd/profiles-1.0.0.xsd">
    <profiles>
        <profile>
            <id>sonar</id>
            <activation>
                <activeByDefault>true</activeByDefault>
            </activation>
            <properties>
                <sonar.host.url>http://localhost:9000/</sonar.host.url>
                <sonar.login>7a981bca217f2e8c653c99dee5ae7062444927c5</sonar.login>
            </properties>
        </profile>
    </profiles>
</profilesXml>